utodata
