Metadata-Version: 2.1
Name: utodata
Version: 0.0.2
Summary: 友道智途-数据平台,数据闭环SDK
Author: uto-dataplatform
Author-email: data-platform@utopilot.ai
